[{"title":"Does this count as country music? #funnysong #cowboy","videoId":"oZXx9PNDR3M","channelTitle":"Carter Vail","tags":["indie","country","sexy","indie pop","indie rock","USA","Lo-Fi","shoegaze","dream pop","american","comedy","singer songwriter","hairy chest","youtubers","Connecticuter","guys who like to flaunt","keep a little dirt under my pillow for the dirt man","handsome guys going viral with funny catchy short songs"]},{"title":"OVERTIME","videoId":"NjXYmfF0I98","channelTitle":"haruno","tags":["japanese","ambient","Lo-Fi","chillout","chill","vocaloid"]},{"title":"Everybody Wants My Body (Because of the Coins in My Body) #funny #funnysong #musician","videoId":"szbEoXeH0dU","channelTitle":"Carter Vail","tags":["indie","country","sexy","indie pop","indie rock","USA","Lo-Fi","shoegaze","dream pop","american","comedy","singer songwriter","hairy chest","youtubers","Connecticuter","guys who like to flaunt","keep a little dirt under my pillow for the dirt man","handsome guys going viral with funny catchy short songs"]},{"title":"Murder on the Dance Floor (triple j Like A Version)","videoId":"37Ym8iHP2E0","channelTitle":"Royel Otis","tags":["seen live","indie pop","indie rock","Lo-Fi","dream pop"]},{"title":"Cha-cha","videoId":"4JxevC3ZGgc","channelTitle":"La Femme","tags":["new wave","french","cold wave","Surf","Lo-Fi","seen live"]},{"title":"Dernière Danse","videoId":"Q4UgorlvQZo","channelTitle":"Ugga","tags":["ugga","folk","acoustic","latgalian","singer-songwriter","Lo-Fi","indie folk","00s","10s","latvian","jaunie","latgola","inde indive"]},{"title":"Disappointment","videoId":"V9RmwausyBI","channelTitle":"Sarcastic Sounds","tags":["Lo-Fi","Hip-Hop","beats"]},{"title":"Thaehan feat. Oogie Boogie - You're Joking !","videoId":"VdzAQ5F6c30","channelTitle":"Thaehan","tags":["electronic","chill","Lo-Fi","french","france","lo-fi hip hop","mixed-chillout"]},{"title":"Think About","videoId":"PccfYKYtU80","channelTitle":"Ugga","tags":["ugga","folk","acoustic","latgalian","singer-songwriter","Lo-Fi","indie folk","00s","10s","latvian","jaunie","latgola","inde indive"]},{"title":"Haze (Original Mix)","videoId":"mVkkXhDLlwQ","channelTitle":"G Mills","tags":["Lo-Fi","electronic","USA","chill","beats","exotica","instrumentals","United States","in english","lo-fi hip hop"]},{"title":"Gravity Falls theme song but it's lofi hip hop","videoId":"e1TH9ivLM98","channelTitle":"L.Dre","tags":["chill","Lo-Fi","remix","lol","disney XD","gravity falls"]},{"title":"lovesick","videoId":"YOSpS0WOnCo","channelTitle":"potsu","tags":["nu jazz","Lo-Fi","chillout","electronic","instrumental","downtempo"]},{"title":"Eternal Youth","videoId":"_BWPNPtsZm8","channelTitle":"RŮDE","tags":["Lo-Fi","american"]},{"title":"Lonely (Original Mix)","videoId":"QgPNGyJdYw8","channelTitle":"idealism","tags":["trip-hop","downtempo","Lo-Fi","Hip-Hop","instrumental hip-hop","beats","ambient","finnish"]},{"title":"in your arms","videoId":"Ce6so35INYU","channelTitle":"Saib","tags":["Lo-Fi","instrumental hip-hop","chillhop","Hip-Hop","instrumental","chillout","beats","morocco"]},{"title":"Crush","videoId":"HEKMZWkHJUM","channelTitle":"Tessa Violet","tags":["pop","alternative","indie pop","techno","indie","Love","Lo-Fi","russian","frauen und technik","bubblegum pop","crushing","daybreak","tiktok","netflix","stalkersong","T Artist"]}]